zxpass/__init__.py
zxpass/plugin.py
zxpass/zxpass.py
qiskit_zx_transpiler-0.0.1.dist-info/LICENSE
qiskit_zx_transpiler-0.0.1.dist-info/METADATA
qiskit_zx_transpiler-0.0.1.dist-info/WHEEL
qiskit_zx_transpiler-0.0.1.dist-info/entry_points.txt
qiskit_zx_transpiler-0.0.1.dist-info/top_level.txt
qiskit_zx_transpiler-0.0.1.dist-info/RECORD
