Metadata-Version: 2.1
Name: qiskit-zx-transpiler
Version: 0.0.1
Summary: A transpiler pass for Qiskit which uses ZX-Calculus for circuit optimization, implemented using PyZX.
Author-email: David Yonge-Mallo <dlyongemallo@users.noreply.github.com>
License: Apache 2.0
Project-URL: Homepage, https://github.com/dlyongemallo/qiskit-zx-transpiler
Project-URL: Repository, https://github.com/dlyongemallo/qiskit-zx-transpiler
Project-URL: Issues, https://github.com/dlyongemallo/qiskit-zx-transpiler/issues
Keywords: qiskit,zx-calculus,quantum circuit optimization,quantum computing
Classifier: Intended Audience :: Science/Research
Classifier: License :: OSI Approved :: Apache Software License
Classifier: Operating System :: MacOS
Classifier: Operating System :: Microsoft :: Windows
Classifier: Operating System :: POSIX :: Linux
Classifier: Programming Language :: Python :: 3 :: Only
Classifier: Programming Language :: Python :: 3.8
Classifier: Programming Language :: Python :: 3.9
Classifier: Programming Language :: Python :: 3.10
Classifier: Programming Language :: Python :: 3.11
Classifier: Programming Language :: Python :: 3.12
Classifier: Topic :: Scientific/Engineering
Requires-Python: >=3.8
License-File: LICENSE
